CHANGELOG
LICENSE
MANIFEST.in
README.md
setup.py
python_taobao.egg-info/PKG-INFO
python_taobao.egg-info/SOURCES.txt
python_taobao.egg-info/dependency_links.txt
python_taobao.egg-info/top_level.txt
taobao/__init__.py