Metadata-Version: 1.1
Name: python-taobao
Version: 0.1.1
Summary: Library for taobao api 
Home-page: https://github.com/buke/python-taobao/
Author: wangbuke
Author-email: wangbuke@gmail.com
License: AGPLv3+
Platform: UNKNOWN
Classifier: Development Status :: 5 - Production/Stable
Classifier: Intended Audience :: Developers
Classifier: License :: OSI Approved :: GNU Affero General Public License v3 or later (AGPLv3+)
Classifier: Operating System :: OS Independent
Classifier: Programming Language :: Python :: 2.6
Classifier: Programming Language :: Python :: 2.7
Classifier: Programming Language :: Python :: 3
Classifier: Topic :: Software Development :: Libraries :: Python Modules
